Metadata-Version: 2.0
Name: txi2p
Version: 0.2.post1
Summary: I2P bindings for Twisted
Home-page: https://github.com/str4d/txi2p
Author: str4d
Author-email: str4d@i2pmail.org
License: ISC
Platform: UNKNOWN
Classifier: Development Status :: 4 - Beta
Classifier: Framework :: Twisted
Classifier: Intended Audience :: Developers
Classifier: License :: OSI Approved :: ISC License (ISCL)
Classifier: Operating System :: OS Independent
Classifier: Programming Language :: Python :: 2.6
Classifier: Programming Language :: Python :: 2.7
Classifier: Programming Language :: Python :: 2 :: Only
Classifier: Topic :: Internet
Requires-Dist: Twisted (>=10.1)
Requires-Dist: Parsley (>=1.2)
